README
setup.py
mypy/__init__.py
mypy/__main__.py
mypy/main.py
mypy_lang.egg-info/PKG-INFO
mypy_lang.egg-info/SOURCES.txt
mypy_lang.egg-info/dependency_links.txt
mypy_lang.egg-info/entry_points.txt
mypy_lang.egg-info/top_level.txt