Metadata-Version: 1.0
Name: mypy-lang
Version: 0.5.0
Summary: Dummy to remind people to switch to 'pip install mypy'
Home-page: UNKNOWN
Author: Guido van Rossum
Author-email: guido@python.org
License: MIT License
Platform: UNKNOWN
